{
  "title": "How to enable God Mode on Windows 11, and what is it?",
  "url": "https://www.xda-developers.com/how-to-enable-god-mode-windows-11-what-is-it/",
  "date": "Thu, 21 Apr 2022 21:30:33 +0000",
  "content": "<p>Windows 11 introduced a new Settings app, which is the way Microsoft wants most users to change settings on their PC. The Settings app has a modern UI and it provides a wide range of options for users to tailor their PC experience, but it&#8217;s not exactly a perfect replacement for the classic Control Panel.</p><p>The post <a rel=\"nofollow\" href=\"https://www.xda-developers.com/how-to-enable-god-mode-windows-11-what-is-it/\">How to enable God Mode on Windows 11, and what is it?</a> appeared first on <a rel=\"nofollow\" href=\"https://www.xda-developers.com\">xda-developers</a>.</p>",
  "image": "https://www.xda-developers.com/files/2022/04/Enable-God-Folder-Windows-11-featured.jpg",
  "description": "Wondering how to use God Mode on Windows 11 or previous versions of Windows? Here's how to enable it and what you can do with it.",
  "publisher": "XDA Developers",
  "publisherUrl": "https://www.xda-developers.com/feed/"
}