{
  "title": "Latest Galaxy Watch 4 update improves Samsung Health, brings March security patch",
  "url": "https://www.xda-developers.com/galaxy-watch-4-update-samsung-health-improvements-march-patch/",
  "date": "Thu, 07 Apr 2022 10:28:09 +0000",
  "content": "<p>The Galaxy Watch 4 is one of the best Wear OS-powered smartwatches on the market right now. It also remains the only smartwatch to run Wear OS 3 out of the box. Packed with the best-in-class hardware, the Galaxy Watch 4 has kept getting better over time with timely software updates. The watch is now</p><p>The post <a rel=\"nofollow\" href=\"https://www.xda-developers.com/galaxy-watch-4-update-samsung-health-improvements-march-patch/\">Latest Galaxy Watch 4 update improves Samsung Health, brings March security patch</a> appeared first on <a rel=\"nofollow\" href=\"https://www.xda-developers.com\">xda-developers</a>.</p>",
  "image": "https://www.xda-developers.com/files/2021/08/Samsung-Galaxy-Watch-4-Sisko-3.jpg",
  "description": "Samsung has started rolling out a new software update to the Galaxy Watch 4. The update carries build number R870XXU1FVC8.",
  "publisher": "XDA Developers",
  "publisherUrl": "https://www.xda-developers.com/feed/"
}