{
  "title": "These apps turn the Galaxy S22’s hole-punch into a battery and notification indicator",
  "url": "https://www.xda-developers.com/samsung-galaxy-s22-energy-ring-aodnotify-battery-notification-indicator/",
  "date": "Sun, 13 Mar 2022 09:00:54 +0000",
  "content": "<p>The Samsung Galaxy S22 series has everything you would expect from a modern flagship smartphone: an incredible display, stellar cameras, and snappy performance. The front camera&#8217;s hole-punch design, however, can still come across as an eyesore to some people. Luckily, customization is a key feature that gives Android smartphones a leg up over their iOS</p><p>The post <a rel=\"nofollow\" href=\"https://www.xda-developers.com/samsung-galaxy-s22-energy-ring-aodnotify-battery-notification-indicator/\">These apps turn the Galaxy S22’s hole-punch into a battery and notification indicator</a> appeared first on <a rel=\"nofollow\" href=\"https://www.xda-developers.com\">xda-developers</a>.</p>",
  "image": "https://www.xda-developers.com/files/2022/02/Galaxy-S22-ultra-xda-11344234534.jpg",
  "description": "Energy Ring and aodNotify help you to repurpose the hole-punch cutout on the Samsung Galaxy S22 as a battery indicator or a notification LED.",
  "publisher": "XDA Developers",
  "publisherUrl": "https://www.xda-developers.com/feed/"
}