{
  "title": "Elon Musk: Tech Visionary Turns Social Media King - NDTV",
  "url": "https://www.ndtv.com/world-news/elon-musk-tech-visionary-turns-social-media-king-2920062",
  "date": "Mon, 25 Apr 2022 23:59:34 GMT",
  "content": "<a href=\"https://www.ndtv.com/world-news/elon-musk-tech-visionary-turns-social-media-king-2920062\" target=\"_blank\">Elon Musk: Tech Visionary Turns Social Media King</a>&nbsp;&nbsp;<font color=\"#6f6f6f\">NDTV</font>",
  "image": "https://c.ndtvimg.com/2022-03/9ckja9fg_elon-musk_625x300_05_March_22.jpg",
  "description": "Sometimes it feels like it's Elon Musk's world and we just live in it. The endlessly innovative, endlessly eccentric billionaire has struck a deal to buy Twitter -- giving him control of the social media network on which the world debates, mobilizes",
  "publisher": "Google News Tech India",
  "publisherUrl": "https://news.google.com/topstories?hl=en-IN&gl=IN&ceid=IN:en"
}