{
  "title": "New tech on the block: IT, AI, digital trans, cyber sec, EdTech, SaaS, CCM - The Tech Panda",
  "url": "https://thetechpanda.com/new-tech-on-the-block-it-ai-digital-trans-cyber-sec-edtech-saas-ccm/36215/",
  "date": "Mon, 25 Apr 2022 19:05:43 GMT",
  "content": "<a href=\"https://thetechpanda.com/new-tech-on-the-block-it-ai-digital-trans-cyber-sec-edtech-saas-ccm/36215/\" target=\"_blank\">New tech on the block: IT, AI, digital trans, cyber sec, EdTech, SaaS, CCM</a>&nbsp;&nbsp;<font color=\"#6f6f6f\">The Tech Panda</font>",
  "image": "https://thetechpanda.com/wp-content/uploads/2022/04/space-5000696_640.png",
  "description": null,
  "publisher": "Google News Tech India",
  "publisherUrl": "https://news.google.com/topstories?hl=en-IN&gl=IN&ceid=IN:en"
}