{
  "title": "Tech companies in Ukraine open economic front in Russian war - TechTarget",
  "url": "https://www.techtarget.com/searchcio/news/252515398/Tech-companies-in-Ukraine-open-economic-front-in-Russian-war",
  "date": "Thu, 31 Mar 2022 19:31:10 GMT",
  "content": "<a href=\"https://www.techtarget.com/searchcio/news/252515398/Tech-companies-in-Ukraine-open-economic-front-in-Russian-war\" target=\"_blank\">Tech companies in Ukraine open economic front in Russian war</a>&nbsp;&nbsp;<font color=\"#6f6f6f\">TechTarget</font>",
  "image": "https://cdn.ttgtmedia.com/ITKE/images/logos/TTlogo-379x201.png",
  "description": "Tech companies in Ukraine continue to operate amid the war with Russia. Read about their experiences and how the IT talent pool is transforming.",
  "publisher": "Google News Tech India",
  "publisherUrl": "https://news.google.com/topstories?hl=en-IN&gl=IN&ceid=IN:en"
}