{
  "title": "Thiel-Backed Fund Looks for Korean Tech Firms to Take Global - Bloomberg",
  "url": "https://www.bloomberg.com/news/articles/2022-04-26/thiel-backed-fund-looks-for-korean-tech-firms-to-take-global",
  "date": "Tue, 26 Apr 2022 22:00:00 GMT",
  "content": "<a href=\"https://www.bloomberg.com/news/articles/2022-04-26/thiel-backed-fund-looks-for-korean-tech-firms-to-take-global\" target=\"_blank\">Thiel-Backed Fund Looks for Korean Tech Firms to Take Global</a>&nbsp;&nbsp;<font color=\"#6f6f6f\">Bloomberg</font>",
  "image": null,
  "description": null,
  "publisher": "Google News Tech India",
  "publisherUrl": "https://news.google.com/topstories?hl=en-IN&gl=IN&ceid=IN:en"
}