{
  "title": "Weekend Investment Alert! 5 Tech Stocks to Explore for Profits - Analytics Insight",
  "url": "https://www.analyticsinsight.net/weekend-investment-alert-5-tech-stocks-to-explore-for-profits/",
  "date": "Fri, 11 Mar 2022 06:14:18 GMT",
  "content": "<a href=\"https://www.analyticsinsight.net/weekend-investment-alert-5-tech-stocks-to-explore-for-profits/\" target=\"_blank\">Weekend Investment Alert! 5 Tech Stocks to Explore for Profits</a>&nbsp;&nbsp;<font color=\"#6f6f6f\">Analytics Insight</font>",
  "image": "https://analyticsinsight.b-cdn.net/wp-content/uploads/2022/03/Weekend-Investment-Alert-5-Tech-Stocks-to-Explore-for-Profits.jpg",
  "description": "Tech stocks are some of the most invested stocks since top tech stocks yield great profits. Investors lookout for the top 5 tech stocks and this article lists the tech stocks to buy for long-term investments.",
  "publisher": "Google News Tech India",
  "publisherUrl": "https://news.google.com/topstories?hl=en-IN&gl=IN&ceid=IN:en"
}