{
  "title": "9-Euro-Ticket",
  "url": "https://www.bahn.com/en/offers/regional/9-euro-ticket-en",
  "date": "Fri, 20 May 2022 11:15:36 +0000",
  "content": "<a href=\"https://news.ycombinator.com/item?id=31445822\">Comments</a>",
  "image": "https://assets.static-bahn.de/.resources/bahn-common/webresources/img/social-media-default.jpg",
  "description": "Energy costs are rising. As one response, the German government is planning to launch a special-offer ticket as part of its support package for bus and rail transport. For 9 euros, you can travel throughout Germany on local/regional trains for a whole month in June, July or August. Sales at Deutsche Bahn will start on 23 May 2022.",
  "publisher": "Hackernews",
  "publisherUrl": "http://news.ycombinator.com/"
}