{
  "title": "Almond.css: Collection of CSS styles to make simple websites look nicer",
  "url": "https://github.com/alvaromontoro/almond.css",
  "date": "Mon, 28 Feb 2022 07:04:55 +0000",
  "content": "<a href=\"https://news.ycombinator.com/item?id=30497165\">Comments</a>",
  "image": "https://opengraph.githubassets.com/f5fb64b1a3a56e4ff0f5f762c384ea0547ce357c0bc33865075db49bd012f438/alvaromontoro/almond.css",
  "description": "Collection of CSS styles to make simple websites look nicer - GitHub - alvaromontoro/almond.css: Collection of CSS styles to make simple websites look nicer",
  "publisher": "Hackernews",
  "publisherUrl": "http://news.ycombinator.com/"
}