{
  "title": "Iced – A cross-platform GUI library for Rust, inspired by Elm",
  "url": "https://github.com/iced-rs/iced",
  "date": "Mon, 11 Apr 2022 00:00:25 +0000",
  "content": "<a href=\"https://news.ycombinator.com/item?id=30983024\">Comments</a>",
  "image": "https://opengraph.githubassets.com/268a88f2c3db8ffb952f9b64c9ae37464a5526abb7d3ea810952c832b5a1b785/iced-rs/iced",
  "description": "A cross-platform GUI library for Rust, inspired by Elm - GitHub - iced-rs/iced: A cross-platform GUI library for Rust, inspired by Elm",
  "publisher": "Hackernews",
  "publisherUrl": "http://news.ycombinator.com/"
}