{
  "title": "Missing Darwin Notebooks Returned to Cambridge University Library",
  "url": "https://www.cam.ac.uk/stories/TreeOfLife",
  "date": "Tue, 5 Apr 2022 06:33:35 +0000",
  "content": "<a href=\"https://news.ycombinator.com/item?id=30915923\">Comments</a>",
  "image": "https://www.cam.ac.uk/sites/www.cam.ac.uk/files/shorthand/231251/fzolcVTTso/assets/Gzo9ynJodx/dsc02935-4096x3072.jpeg",
  "description": "Charles Darwin’s iconic Tree of Life notebooks anonymously left in a pink gift bag, 15 months after launch of a worldwide appeal to find them",
  "publisher": "Hackernews",
  "publisherUrl": "http://news.ycombinator.com/"
}