{
  "title": "Nvidia transitioning to official, open-source Linux GPU kernel driver",
  "url": "https://www.phoronix.com/scan.php?page=article&item=nvidia-open-kernel&num=1",
  "date": "Wed, 11 May 2022 19:59:46 +0000",
  "content": "<a href=\"https://news.ycombinator.com/item?id=31344981\">Comments</a>",
  "image": "https://www.phoronix.net/image.php?id=nvidia-open-kernel&image=nvidia_open_1",
  "description": null,
  "publisher": "Hackernews",
  "publisherUrl": "http://news.ycombinator.com/"
}