{
  "title": "Obsidian Dataview: Turn Obsidian Vault into a database which you can query from",
  "url": "https://github.com/blacksmithgu/obsidian-dataview",
  "date": "Tue, 17 May 2022 09:09:16 +0000",
  "content": "<a href=\"https://news.ycombinator.com/item?id=31407781\">Comments</a>",
  "image": "https://opengraph.githubassets.com/4e33079714a5a9a6567df222a2363c9e50db8df0629096f653e717be764e6b87/blacksmithgu/obsidian-dataview",
  "description": "A high-performance data index and query language over Markdown files, for https://obsidian.md/. - GitHub - blacksmithgu/obsidian-dataview: A high-performance data index and query language over Mark...",
  "publisher": "Hackernews",
  "publisherUrl": "http://news.ycombinator.com/"
}