{
  "title": "Patenting Your Perpetual Motion Machine",
  "url": "https://unmakeme.com/2022/05/09/patenting-your-perpetual-motion-machine/",
  "date": "Mon, 9 May 2022 14:04:02 +0000",
  "content": "<a href=\"https://news.ycombinator.com/item?id=31314122\">Comments</a>",
  "image": "https://unmakeme.files.wordpress.com/2022/05/image-11.png",
  "description": "As a patent attorney, I am bound by two different sets of laws–the human and the physical–and I foolishly expected others to feel the same. I should have known better, and I am sorry.",
  "publisher": "Hackernews",
  "publisherUrl": "http://news.ycombinator.com/"
}