{
  "title": "Please don’t let anyone Americanise it (1992)",
  "url": "https://news.lettersofnote.com/p/please-dont-let-anyone-americanise",
  "date": "Thu, 12 May 2022 08:19:26 +0000",
  "content": "<a href=\"https://news.ycombinator.com/item?id=31350746\">Comments</a>",
  "image": "https://substackcdn.com/image/fetch/w_1456,c_limit,f_auto,q_auto:good,fl_progressive:steep/https%3A%2F%2Fbucketeer-e05bbc84-baa3-437e-9518-adb32be77984.s3.amazonaws.com%2Fpublic%2Fimages%2F463b3bfb-54af-46ca-8ea3-3c64abde3621_423x594.jpeg",
  "description": "Entertaining feedback from Douglas Adams",
  "publisher": "Hackernews",
  "publisherUrl": "http://news.ycombinator.com/"
}