{
  "title": "'Quantum friction' slows water flow through carbon nanotubes",
  "url": "https://phys.org/news/2022-02-quantum-friction-carbon-nanotubes-long-standing.html",
  "date": "Thu, 3 Feb 2022 19:40:15 +0000",
  "content": "<a href=\"https://news.ycombinator.com/item?id=30197656\">Comments</a>",
  "image": "https://scx2.b-cdn.net/gfx/news/hires/2022/quantum-friction-slows.jpg",
  "description": "For 15 years, scientists have been baffled by the mysterious way water flows through the tiny passages of carbon nanotubes—pipes with walls that can be just one atom thick. The streams have confounded all theories of fluid dynamics; paradoxically, fluid passes more easily through narrower nanotubes, and in all nanotubes it moves with almost no friction. What friction there is has also defied explanation.",
  "publisher": "Hackernews",
  "publisherUrl": "http://news.ycombinator.com/"
}