{
  "title": "RIP Good Times (2008)",
  "url": "https://articles.sequoiacap.com/rip-good-times",
  "date": "Thu, 19 May 2022 17:56:00 +0000",
  "content": "<a href=\"https://news.ycombinator.com/item?id=31437946\">Comments</a>",
  "image": null,
  "description": "Back in 2008, Sequoia Capital shared with its portfolio companies tips for surviving the economic downturn. Here's the original RIP Good Times presentation. ",
  "publisher": "Hackernews",
  "publisherUrl": "http://news.ycombinator.com/"
}