{
  "title": "Show HN: Bionic Reading – Formats text to make it faster to read",
  "url": "https://bionic-reading.com/",
  "date": "Thu, 24 Mar 2022 08:04:34 +0000",
  "content": "<a href=\"https://news.ycombinator.com/item?id=30787290\">Comments</a>",
  "image": "https://bionic-reading.com/wp-content/uploads/2021/09/renato-profilfoto-01-768x1024.jpg",
  "description": "Did you know that your brain reads faster than your eye? We humans store learned words and so just a few letters are enough to ecognize whole words.",
  "publisher": "Hackernews",
  "publisherUrl": "http://news.ycombinator.com/"
}