{
  "title": "Valencia's irrigation system is now a model for sustainable farming",
  "url": "https://www.bbc.com/travel/article/20220220-valencias-la-huerta-spains-ingenious-water-maze",
  "date": "Mon, 21 Feb 2022 19:11:20 +0000",
  "content": "<a href=\"https://news.ycombinator.com/item?id=30419451\">Comments</a>",
  "image": "https://ychef.files.bbci.co.uk/live/624x351/p0bn16fz.jpg",
  "description": "Invented by the region's Moorish rulers 1,200 years ago, Valencia's irrigation system is now a model for sustainable farming.",
  "publisher": "Hackernews",
  "publisherUrl": "http://news.ycombinator.com/"
}