{
  "title": "Buzzing Stocks | Vedanta, Hero MotoCorp, L&T Finance Holdings and others in news today - Moneycontrol.com",
  "url": "https://www.moneycontrol.com/news/photos/business/stocks/buzzing-stocks-vedanta-hero-motocorp-lt-finance-holdings-and-others-in-news-today-8145441.html",
  "date": "Tue, 22 Feb 2022 03:14:43 GMT",
  "content": "<a href=\"https://www.moneycontrol.com/news/photos/business/stocks/buzzing-stocks-vedanta-hero-motocorp-lt-finance-holdings-and-others-in-news-today-8145441.html\" target=\"_blank\">Buzzing Stocks | Vedanta, Hero MotoCorp, L&T Finance Holdings and others in news today</a>&nbsp;&nbsp;<font color=\"#6f6f6f\">Moneycontrol.com</font>",
  "image": "https://images.moneycontrol.com/static-mcnews/2021/03/BUZZING-STOCKS-770x433.jpg",
  "description": "Stocks In the News: Check out the companies making headlines before the opening bell.",
  "publisher": "Google News Finance India",
  "publisherUrl": "https://news.google.com/search?q=finance&hl=en-IN&gl=INS&ceid=IN:en"
}