{
  "title": "IFC makes debt investment in Blackstone-backed housing finance firm - VCCircle",
  "url": "https://www.vccircle.com/ifc-makes-debt-investment-in-blackstone-backed-housing-finance-firm",
  "date": "Thu, 28 Apr 2022 05:45:48 GMT",
  "content": "<a href=\"https://www.vccircle.com/ifc-makes-debt-investment-in-blackstone-backed-housing-finance-firm\" target=\"_blank\">IFC makes debt investment in Blackstone-backed housing finance firm</a>&nbsp;&nbsp;<font color=\"#6f6f6f\">VCCircle</font>",
  "image": "https://assets.vccircle.com/uploads/2022/04/blackstonereuters.jpg",
  "description": "International Finance Corporation (IFC), private investment arm of the World Bank, has proposed to make a debt investment of up",
  "publisher": "Google News Finance India",
  "publisherUrl": "https://news.google.com/search?q=finance&hl=en-IN&gl=INS&ceid=IN:en"
}