{
  "title": "As states push their own privacy laws, health tech companies fear compliance nightmare - STAT",
  "url": "https://www.statnews.com/2022/02/18/health-tech-privacy-regulation-patient/",
  "date": "Fri, 18 Feb 2022 09:32:04 GMT",
  "content": "<a href=\"https://www.statnews.com/2022/02/18/health-tech-privacy-regulation-patient/\" target=\"_blank\">As states push their own privacy laws, health tech companies fear compliance nightmare</a>&nbsp;&nbsp;<font color=\"#6f6f6f\">STAT</font>",
  "image": "https://www.statnews.com/wp-content/uploads/2022/02/HOSPITAL_ROOM_phone_w_band-1024x576.jpg",
  "description": "Smaller health tech companies are preparing to devote significant staff and resources to comply with a patchwork of state data privacy laws.",
  "publisher": "Google News Tech USA",
  "publisherUrl": "https://news.google.com/topstories?hl=en-US&gl=US&ceid=US:en"
}