{
  "title": "Behind Russia's 'digital iron curtain', tech workarounds thrive - Reuters.com",
  "url": "https://www.reuters.com/legal/litigation/behind-russias-digital-iron-curtain-tech-workarounds-thrive-2022-03-23/",
  "date": "Wed, 23 Mar 2022 21:16:00 GMT",
  "content": "<a href=\"https://www.reuters.com/legal/litigation/behind-russias-digital-iron-curtain-tech-workarounds-thrive-2022-03-23/\" target=\"_blank\">Behind Russia's 'digital iron curtain', tech workarounds thrive</a>&nbsp;&nbsp;<font color=\"#6f6f6f\">Reuters.com</font>",
  "image": "https://www.reuters.com/resizer/cWZ-A2k_Xh2QSSuuEj-hb_55igQ=/728x381/smart/filters:quality(80)/cloudfront-us-east-2.images.arcpublishing.com/reuters/I4QIECPLORN25M2XKGJH5FWRHI.jpg",
  "description": "As a busy tour guide in St. Petersburg, Vsevolod Gavrilov never paid much attention to the day's headlines, instead tracking travel influencers on social media platforms and messaging his friends on the Telegram app.",
  "publisher": "Google News Tech USA",
  "publisherUrl": "https://news.google.com/topstories?hl=en-US&gl=US&ceid=US:en"
}