{
  "title": "Elon Musk’s $44 billion Twitter takeover is one of the biggest tech acquisitions of all time. Here’s where the billionaire’s deal ranks in tech history - Fortune",
  "url": "https://fortune.com/2022/04/25/elon-musk-twitter-takeover-rank-biggest-tech-acquisitions-ever/",
  "date": "Mon, 25 Apr 2022 21:59:53 GMT",
  "content": "<a href=\"https://fortune.com/2022/04/25/elon-musk-twitter-takeover-rank-biggest-tech-acquisitions-ever/\" target=\"_blank\">Elon Musk’s $44 billion Twitter takeover is one of the biggest tech acquisitions of all time. Here’s where the billionaire’s deal ranks in tech history</a>&nbsp;&nbsp;<font color=\"#6f6f6f\">Fortune</font>",
  "image": "https://content.fortune.com/wp-content/uploads/2022/04/Musk-acquisition-e1650920925559.jpg?resize=1200,600",
  "description": "The Tesla CEO made history on Monday with his Twitter takeover.",
  "publisher": "Google News Tech USA",
  "publisherUrl": "https://news.google.com/topstories?hl=en-US&gl=US&ceid=US:en"
}