{
  "title": "EU law targets Big Tech over hate speech, disinformation - NPR",
  "url": "https://www.npr.org/2022/04/23/1094485542/eu-law-big-tech-hate-speech-disinformation",
  "date": "Sat, 23 Apr 2022 17:48:36 GMT",
  "content": "<ol><li><a href=\"https://www.npr.org/2022/04/23/1094485542/eu-law-big-tech-hate-speech-disinformation\" target=\"_blank\">EU law targets Big Tech over hate speech, disinformation</a>&nbsp;&nbsp;<font color=\"#6f6f6f\">NPR</font></li><li><a href=\"https://www.cnn.com/2022/04/23/business/eu-tech-regulation/index.html\" target=\"_blank\">Europe agrees to sweeping new regulations for tech platforms</a>&nbsp;&nbsp;<font color=\"#6f6f6f\">CNN</font></li><li><a href=\"https://www.nytimes.com/2022/04/22/technology/tech-regulation-europe-us.html\" target=\"_blank\">As Europe Approves New Tech Laws, the U.S. Falls Further Behind</a>&nbsp;&nbsp;<font color=\"#6f6f6f\">The New York Times</font></li><li><a href=\"https://www.nbcnews.com/tech/tech-news/new-eu-landmark-law-targets-big-tech-firms-hate-speech-disinformation-rcna25705\" target=\"_blank\">New E.U. landmark law targets Big Tech firms over hate speech, disinformation</a>&nbsp;&nbsp;<font color=\"#6f6f6f\">NBC News</font></li><li><a href=\"https://www.cnbc.com/2022/04/22/digital-services-act-eu-agrees-new-rules-for-tackling-illegal-content.html\" target=\"_blank\">EU agrees on landmark law aimed at forcing Big Tech firms to tackle illegal content</a>&nbsp;&nbsp;<font color=\"#6f6f6f\">CNBC</font></li><li><strong><a href=\"https://news.google.com/stories/CAAqNggKIjBDQklTSGpvSmMzUnZjbmt0TXpZd1NoRUtEd2o0M0xpQUJSSHJGdTVXdGpaU1NpZ0FQAQ?oc=5\" target=\"_blank\">View Full Coverage on Google News</a></strong></li></ol>",
  "image": "https://media.npr.org/assets/img/2022/04/23/ap22112518307778_wide-26e7f43ec22947a73d8df941f91da02d1a6129a8.jpg?s=1400",
  "description": "The Digital Services Act, one half of an overhaul for the European Union's digital rulebook, helps cement Europe's reputation as the global leader in efforts to rein in the power of digital platforms.",
  "publisher": "Google News Tech USA",
  "publisherUrl": "https://news.google.com/topstories?hl=en-US&gl=US&ceid=US:en"
}