{
  "title": "Gardner-Webb Drops Series Opener Friday At No. 7 Georgia Tech - Gardner Webb University Bulldogs",
  "url": "https://gwusports.com/news/2022/2/25/baseball-gardner-webb-drops-series-opener-friday-at-no-7-georgia-tech.aspx",
  "date": "Sat, 26 Feb 2022 03:48:36 GMT",
  "content": "<a href=\"https://gwusports.com/news/2022/2/25/baseball-gardner-webb-drops-series-opener-friday-at-no-7-georgia-tech.aspx\" target=\"_blank\">Gardner-Webb Drops Series Opener Friday At No. 7 Georgia Tech</a>&nbsp;&nbsp;<font color=\"#6f6f6f\">Gardner Webb University Bulldogs</font>",
  "image": "https://gwusports.com/images/2022/2/25/Simeone_2.jpg?preset=large.socialmediaimage",
  "description": "ATLANTA – Gardner-Webb faced its second top-10 opponent of the season on Friday afternoon, falling at 7th-ranked Georgia Tech, 14-0, in its first road game of 2022.",
  "publisher": "Google News Tech USA",
  "publisherUrl": "https://news.google.com/topstories?hl=en-US&gl=US&ceid=US:en"
}