{
  "title": "Harding Drops Tight Game at Tech - Harding University Athletics",
  "url": "https://hardingsports.com/news/2022/2/8/mens-basketball-harding-drops-tight-game-at-tech.aspx",
  "date": "Wed, 09 Feb 2022 02:17:24 GMT",
  "content": "<a href=\"https://hardingsports.com/news/2022/2/8/mens-basketball-harding-drops-tight-game-at-tech.aspx\" target=\"_blank\">Harding Drops Tight Game at Tech</a>&nbsp;&nbsp;<font color=\"#6f6f6f\">Harding University Athletics</font>",
  "image": "https://hardingsports.com/images/2022/2/8/2021_22_Men_s_Basketball_at_Arkansas_Tech.jpg?preset=large.socialmediaimage",
  "description": "RUSSELLVILLE, Ark. – In a game with 19 lead changes, Arkansas Tech held Harding scoreless for the last two minutes and defeated the Bisons 68-63 in Great American Conference men's basketball action at Tucker Coliseum.",
  "publisher": "Google News Tech USA",
  "publisherUrl": "https://news.google.com/topstories?hl=en-US&gl=US&ceid=US:en"
}