{
  "title": "Holding food and tech to the same climate standards is counterproductive | Greenbiz - GreenBiz",
  "url": "https://www.greenbiz.com/article/holding-food-and-tech-same-climate-standards-counterproductive",
  "date": "Fri, 18 Feb 2022 01:30:00 GMT",
  "content": "<a href=\"https://www.greenbiz.com/article/holding-food-and-tech-same-climate-standards-counterproductive\" target=\"_blank\">Holding food and tech to the same climate standards is counterproductive | Greenbiz</a>&nbsp;&nbsp;<font color=\"#6f6f6f\">GreenBiz</font>",
  "image": "https://www.greenbiz.com/sites/default/files/styles/og_image_1200x630/public/2022-02/Apples%20and%20Oranges.jpg?itok=XNnWdm3o",
  "description": "A new report from New Climate Institute tries to compare sectors apples to apples when food and tech can be like oranges and bananas.",
  "publisher": "Google News Tech USA",
  "publisherUrl": "https://news.google.com/topstories?hl=en-US&gl=US&ceid=US:en"
}