{
  "title": "How shunning Russia could offer the U.S. tech giants an easy win - POLITICO",
  "url": "https://www.politico.com/news/2022/03/04/u-s-tech-russia-money-00014067",
  "date": "Fri, 04 Mar 2022 09:30:00 GMT",
  "content": "<a href=\"https://www.politico.com/news/2022/03/04/u-s-tech-russia-money-00014067\" target=\"_blank\">How shunning Russia could offer the U.S. tech giants an easy win</a>&nbsp;&nbsp;<font color=\"#6f6f6f\">POLITICO</font>",
  "image": "https://static.politico.com/f4/41/c45f225b484cb755f6cc2fecc298/220303-socialmediarussia-ap-773.jpg",
  "description": "Apple, Google, Meta and Netflix combined would lose between 1 percent to 2 percent of their multibillion-dollar revenues if they were to remove all of their services from Russia, according to one estimate.",
  "publisher": "Google News Tech USA",
  "publisherUrl": "https://news.google.com/topstories?hl=en-US&gl=US&ceid=US:en"
}