{
  "title": "Inside the fierce, messy fight over “healthy” sugar tech - MIT Technology Review",
  "url": "https://www.technologyreview.com/2022/04/11/1048913/inside-the-fierce-messy-fight-over-healthy-sugar-tech/",
  "date": "Mon, 11 Apr 2022 09:00:00 GMT",
  "content": "<a href=\"https://www.technologyreview.com/2022/04/11/1048913/inside-the-fierce-messy-fight-over-healthy-sugar-tech/\" target=\"_blank\">Inside the fierce, messy fight over “healthy” sugar tech</a>&nbsp;&nbsp;<font color=\"#6f6f6f\">MIT Technology Review</font>",
  "image": "https://wp.technologyreview.com/wp-content/uploads/2022/04/Sugar_0125_wk-crop.jpg?resize=1200,600",
  "description": "Yi-Heng “Percival” Zhang was a leader in rare sugar research. Then things got sticky.",
  "publisher": "Google News Tech USA",
  "publisherUrl": "https://news.google.com/topstories?hl=en-US&gl=US&ceid=US:en"
}