{
  "title": "Q&A with Seattle investor Naynika Chaubey, whose clean tech firm just raised $300M - GeekWire",
  "url": "https://www.geekwire.com/2022/qa-with-seattle-investor-naynika-chaubey-whose-clean-tech-firm-just-raised-300m/",
  "date": "Sat, 02 Apr 2022 14:00:00 GMT",
  "content": "<a href=\"https://www.geekwire.com/2022/qa-with-seattle-investor-naynika-chaubey-whose-clean-tech-firm-just-raised-300m/\" target=\"_blank\">Q&A with Seattle investor Naynika Chaubey, whose clean tech firm just raised $300M</a>&nbsp;&nbsp;<font color=\"#6f6f6f\">GeekWire</font>",
  "image": "https://cdn.geekwire.com/wp-content/uploads/2022/04/Evok-Innovations-team-1.jpg",
  "description": "The venture capital firm Evok Innovations this week announced a $300 million fund to invest in clean-tech in North America. The Vancouver, B.C. firm launched in 2016 and previously raised an inaugural…",
  "publisher": "Google News Tech USA",
  "publisherUrl": "https://news.google.com/topstories?hl=en-US&gl=US&ceid=US:en"
}