{
  "title": "S&P 500 rises to start week, Nasdaq gains 1.9% on tech comeback - CNBC",
  "url": "https://www.cnbc.com/2022/04/03/stock-market-futures-open-to-close-news.html",
  "date": "Sun, 03 Apr 2022 22:02:45 GMT",
  "content": "<a href=\"https://www.cnbc.com/2022/04/03/stock-market-futures-open-to-close-news.html\" target=\"_blank\">S&P 500 rises to start week, Nasdaq gains 1.9% on tech comeback</a>&nbsp;&nbsp;<font color=\"#6f6f6f\">CNBC</font>",
  "image": "https://image.cnbcfm.com/api/v1/image/107041659-1649102825721-a2_img_10_57_40_1297655_1000-1649102689303.jpg?v=1649102868&w=1920&h=1080",
  "description": "The S&P 500 and Nasdaq Composite gained on Monday as traders shook off recession fears and bought technology shares that were beaten up in the first quarter.",
  "publisher": "Google News Tech USA",
  "publisherUrl": "https://news.google.com/topstories?hl=en-US&gl=US&ceid=US:en"
}