{
  "title": "Tech Stocks Get a Bear-Market Scare. What Could Come Next. - Barron's",
  "url": "https://www.barrons.com/articles/tech-stocks-get-a-bear-market-scare-what-could-come-next-51645821852",
  "date": "Fri, 25 Feb 2022 20:44:00 GMT",
  "content": "<a href=\"https://www.barrons.com/articles/tech-stocks-get-a-bear-market-scare-what-could-come-next-51645821852\" target=\"_blank\">Tech Stocks Get a Bear-Market Scare. What Could Come Next.</a>&nbsp;&nbsp;<font color=\"#6f6f6f\">Barron's</font>",
  "image": "https://images.barrons.com/im-493179/social",
  "description": "Rising interest rates and Taiwan are still worries. Cybersecurity stocks stand to benefit. ",
  "publisher": "Google News Tech USA",
  "publisherUrl": "https://news.google.com/topstories?hl=en-US&gl=US&ceid=US:en"
}