{
  "title": "Tech Maintains Lead at Watersound Invitational – Men's Golf — Georgia Tech Yellow Jackets - Georgia Tech Official Athletic Site",
  "url": "https://ramblinwreck.com/tech-maintains-lead-at-watersound-invitational-022122/",
  "date": "Tue, 22 Feb 2022 00:01:28 GMT",
  "content": "<a href=\"https://ramblinwreck.com/tech-maintains-lead-at-watersound-invitational-022122/\" target=\"_blank\">Tech Maintains Lead at Watersound Invitational – Men's Golf — Georgia Tech Yellow Jackets</a>&nbsp;&nbsp;<font color=\"#6f6f6f\">Georgia Tech Official Athletic Site</font>",
  "image": "https://ramblinwreck.com/amt-media/425246/",
  "description": "No. 17 Jackets post four subpar rounds Monday, three among top 10 individuals after 36 holes",
  "publisher": "Google News Tech USA",
  "publisherUrl": "https://news.google.com/topstories?hl=en-US&gl=US&ceid=US:en"
}