{
  "title": "Baselane Intros Finance Management Platform for Landlords - PYMNTS.com",
  "url": "https://www.pymnts.com/real-estate/2022/baselane-intros-finance-management-platform-for-landlords/",
  "date": "Tue, 15 Mar 2022 19:11:56 GMT",
  "content": "<a href=\"https://www.pymnts.com/real-estate/2022/baselane-intros-finance-management-platform-for-landlords/\" target=\"_blank\">Baselane Intros Finance Management Platform for Landlords</a>&nbsp;&nbsp;<font color=\"#6f6f6f\">PYMNTS.com</font>",
  "image": "https://securecdn.pymnts.com/wp-content/uploads/2022/03/Baselane-finance-mangement-landlords-property-rentalsjpg-1000x600.jpg",
  "description": "Baselane, a financial platform for landlords and real estate investors, will now offer fully integrated banking services tailored to specific property needs.",
  "publisher": "Google News Finance USA",
  "publisherUrl": "https://news.google.com/search?q=finance&hl=en-US&gl=US&ceid=US:en"
}