{
  "title": "CNBC’s Jim Cramer says these four financial GARP stocks are investable - CNBC",
  "url": "https://www.cnbc.com/2022/04/12/cnbcs-jim-cramer-says-these-four-financial-garp-stocks-are-investable.html",
  "date": "Wed, 13 Apr 2022 00:07:00 GMT",
  "content": "<a href=\"https://www.cnbc.com/2022/04/12/cnbcs-jim-cramer-says-these-four-financial-garp-stocks-are-investable.html\" target=\"_blank\">CNBC’s Jim Cramer says these four financial GARP stocks are investable</a>&nbsp;&nbsp;<font color=\"#6f6f6f\">CNBC</font>",
  "image": "https://image.cnbcfm.com/api/v1/image/102483712-166415240.jpg?v=1574344945&w=1920&h=1080",
  "description": "\"I think it's a good time to pay some attention to the underappreciated financials with GARP appeal,\" the \"Mad Money\" host said.",
  "publisher": "Google News Finance USA",
  "publisherUrl": "https://news.google.com/search?q=finance&hl=en-US&gl=US&ceid=US:en"
}