{
  "title": "CPI inflation, Disney and Peloton earnings: What to know this week - Yahoo Finance",
  "url": "https://finance.yahoo.com/news/cpi-inflation-disney-earnings-what-to-know-this-week-162736428.html",
  "date": "Sun, 06 Feb 2022 16:27:36 GMT",
  "content": "<a href=\"https://finance.yahoo.com/news/cpi-inflation-disney-earnings-what-to-know-this-week-162736428.html\" target=\"_blank\">CPI inflation, Disney and Peloton earnings: What to know this week</a>&nbsp;&nbsp;<font color=\"#6f6f6f\">Yahoo Finance</font>",
  "image": "https://s.yimg.com/ny/api/res/1.2/B6tH_Z0nrjnUTFgPw.nykg--/YXBwaWQ9aGlnaGxhbmRlcjt3PTEyMDA7aD02NzU-/https://s.yimg.com/os/creatr-uploaded-images/2021-12/8e445760-683d-11ec-a7d5-e33bbcac02f6",
  "description": "Investors this week are set to monitor another set of inflation data alongside a packed docket of quarterly earnings results, with names from Disney to Uber, Lyft and Peloton all set to post their reports.",
  "publisher": "Google News Finance USA",
  "publisherUrl": "https://news.google.com/search?q=finance&hl=en-US&gl=US&ceid=US:en"
}