{
  "title": "Net zero in the finance sector, getting tax back and corporate loyalty - The Irish Times",
  "url": "https://www.irishtimes.com/business/markets/net-zero-in-the-finance-sector-getting-tax-back-and-corporate-loyalty-1.4795306",
  "date": "Mon, 07 Feb 2022 06:27:16 GMT",
  "content": "<a href=\"https://www.irishtimes.com/business/markets/net-zero-in-the-finance-sector-getting-tax-back-and-corporate-loyalty-1.4795306\" target=\"_blank\">Net zero in the finance sector, getting tax back and corporate loyalty</a>&nbsp;&nbsp;<font color=\"#6f6f6f\">The Irish Times</font>",
  "image": "https://www.irishtimes.com/image-creator/?id=1.4795305&origw=1440",
  "description": "Business Today: the best news, analysis and comment from The Irish Times business desk",
  "publisher": "Google News Finance USA",
  "publisherUrl": "https://news.google.com/search?q=finance&hl=en-US&gl=US&ceid=US:en"
}