{
  "title": "Russia war bolsters need to combat illicit finance: Treasury - Fortune",
  "url": "https://fortune.com/2022/05/14/russia-war-bolsters-need-to-combat-illicit-finance-treasury/",
  "date": "Sat, 14 May 2022 14:10:13 GMT",
  "content": "<a href=\"https://fortune.com/2022/05/14/russia-war-bolsters-need-to-combat-illicit-finance-treasury/\" target=\"_blank\">Russia war bolsters need to combat illicit finance: Treasury</a>&nbsp;&nbsp;<font color=\"#6f6f6f\">Fortune</font>",
  "image": "https://content.fortune.com/wp-content/uploads/2022/05/AP22131511571366.jpg?resize=1200,600",
  "description": "Crypto is a limited work-around for the sanctioned.",
  "publisher": "Google News Finance USA",
  "publisherUrl": "https://news.google.com/search?q=finance&hl=en-US&gl=US&ceid=US:en"
}