{
  "title": "SA's new finance bylaws, explained – The GW Hatchet - GW Hatchet",
  "url": "https://www.gwhatchet.com/2022/02/07/the-student-associations-new-finance-bylaws-explained/",
  "date": "Mon, 07 Feb 2022 07:13:53 GMT",
  "content": "<a href=\"https://www.gwhatchet.com/2022/02/07/the-student-associations-new-finance-bylaws-explained/\" target=\"_blank\">SA's new finance bylaws, explained – The GW Hatchet</a>&nbsp;&nbsp;<font color=\"#6f6f6f\">GW Hatchet</font>",
  "image": "https://www.gwhatchet.com/wp-content/uploads/2022/02/020722_YanXu_CB-1000x670.jpg",
  "description": "The SA Senate will create a guide for student organizations requesting funds and a new code to clarify recent finance policy updates.",
  "publisher": "Google News Finance USA",
  "publisherUrl": "https://news.google.com/search?q=finance&hl=en-US&gl=US&ceid=US:en"
}