{
  "title": "Stock market returns to be ‘violently flat’ amid slowing growth: Strategist - Yahoo Finance",
  "url": "https://finance.yahoo.com/news/stock-market-returns-to-be-violently-flat-amid-slowing-growth-strategist-162744061.html",
  "date": "Wed, 06 Apr 2022 16:27:44 GMT",
  "content": "<a href=\"https://finance.yahoo.com/news/stock-market-returns-to-be-violently-flat-amid-slowing-growth-strategist-162744061.html\" target=\"_blank\">Stock market returns to be ‘violently flat’ amid slowing growth: Strategist</a>&nbsp;&nbsp;<font color=\"#6f6f6f\">Yahoo Finance</font>",
  "image": "https://s.yimg.com/ny/api/res/1.2/v03zicmmN0oCz4GKFes0ew--/YXBwaWQ9aGlnaGxhbmRlcjt3PTEyMDA7aD04MDA-/https://s.yimg.com/os/creatr-uploaded-images/2022-03/79b02140-a095-11ec-bebf-7aa2d7122451",
  "description": "While some experts are beginning to sound the alarm over the threat of stagflation for the remainder of 2022, a combination of surging inflation and slowing growth poses an ever-growing risk to markets. 22V Research founder Dennis DeBusschere believes that investors should indeed expect stock market returns to be muted in the medium term.",
  "publisher": "Google News Finance USA",
  "publisherUrl": "https://news.google.com/search?q=finance&hl=en-US&gl=US&ceid=US:en"
}