{
  "title": "Ukraine finance minister: sanctions came too late - Marketplace",
  "url": "https://www.marketplace.org/2022/03/04/ukraine-finance-minister-sanctions-came-too-late/",
  "date": "Fri, 04 Mar 2022 17:54:22 GMT",
  "content": "<a href=\"https://www.marketplace.org/2022/03/04/ukraine-finance-minister-sanctions-came-too-late/\" target=\"_blank\">Ukraine finance minister: sanctions came too late</a>&nbsp;&nbsp;<font color=\"#6f6f6f\">Marketplace</font>",
  "image": "https://www.marketplace.org/wp-content/uploads/2022/03/GettyImages-1230941817-1.jpg?w=1200",
  "description": "Ukraine's finance minister calls for more \"severe\" Western sanctions against Russia, warning time is of the essence.",
  "publisher": "Google News Finance USA",
  "publisherUrl": "https://news.google.com/search?q=finance&hl=en-US&gl=US&ceid=US:en"
}