{
  "title": "Ways to finance an engagement ring - Bankrate.com",
  "url": "https://www.bankrate.com/loans/personal-loans/engagement-ring/",
  "date": "Wed, 11 May 2022 22:09:16 GMT",
  "content": "<a href=\"https://www.bankrate.com/loans/personal-loans/engagement-ring/\" target=\"_blank\">Ways to finance an engagement ring</a>&nbsp;&nbsp;<font color=\"#6f6f6f\">Bankrate.com</font>",
  "image": "https://www.bankrate.com/2022/05/11175122/ways-to-finance-an-engagement-ring.jpg",
  "description": "If you need to finance an engagement ring, consider your options to find the best for your needs.",
  "publisher": "Google News Finance USA",
  "publisherUrl": "https://news.google.com/search?q=finance&hl=en-US&gl=US&ceid=US:en"
}