{
  "title": "12 Great Weekend Deals on Smol iPads, TVs, and Theraguns",
  "url": "https://www.wired.com/story/weekend-deals-may-7-2022",
  "date": "Sat, 07 May 2022 11:00:00 +0000",
  "content": "Now is a great time to upgrade your home viewing, gaming, or relaxing with a couple of our favorite fun-size devices.",
  "image": "https://media.wired.com/photos/618c00daf55c11d0e81b3a14/191:100/w_1280,c_limit/Gear-Beats-Fit-Pro-white.jpg",
  "description": "Now is a great time to upgrade your home viewing, gaming, or relaxing with a couple of our favorite fun-size devices.",
  "publisher": "Wired",
  "publisherUrl": "https://www.wired.com/"
}