{
  "title": "6 Free Ways to Practice Sign Language Online",
  "url": "https://www.wired.com/story/how-to-learn-sign-language-free",
  "date": "Sun, 03 Apr 2022 12:00:00 +0000",
  "content": "You don’t need to spend any money to start learning American Sign Language (ASL) with these resources.",
  "image": "https://media.wired.com/photos/624764ed48046e8802c9c5b8/191:100/w_1280,c_limit/Learn-ASL-Online-Gear-495674588.jpg",
  "description": "You don’t need to spend any money to start learning American Sign Language (ASL) with these resources.",
  "publisher": "Wired",
  "publisherUrl": "https://www.wired.com/"
}