{
  "title": "I Played Halo With My Spouse 17 Years After We Almost Broke Up Over It",
  "url": "https://www.wired.com/story/halo-almost-broke-up-game-design",
  "date": "Sat, 23 Apr 2022 11:00:00 +0000",
  "content": "I wasn't ready for it 17 years ago, when my then boyfriend and I nearly broke up over it. But now I can play until I throw up.",
  "image": "https://media.wired.com/photos/6261f63b3fe832fc9511a693/191:100/w_1280,c_limit/Halo-Breakup-Games-Culture-155038165.jpg",
  "description": "I wasn't ready for it 17 years ago, when my then boyfriend and I nearly broke up over it. But now I can play until I throw up.",
  "publisher": "Wired",
  "publisherUrl": "https://www.wired.com/"
}