{
  "title": "NFTs Don’t Work the Way You Might Think They Do",
  "url": "https://www.wired.com/story/nfts-dont-work-the-way-you-think-they-do",
  "date": "Sat, 12 Mar 2022 13:00:00 +0000",
  "content": "We bust the biggest misconceptions about what \"minting\" actually means.",
  "image": "https://media.wired.com/photos/622bde93d53a49d05c484009/191:100/w_1280,c_limit/NFTs-Don't-Work-They-Way-You-Think-Gear-1239020052.jpg",
  "description": "We bust the biggest misconceptions about what \"minting\" actually means.",
  "publisher": "Wired",
  "publisherUrl": "https://www.wired.com/"
}