{
  "title": "The Best Fitness Trackers and Watches for Everyone",
  "url": "https://www.wired.com/gallery/best-fitness-tracker",
  "date": "Sun, 24 Apr 2022 11:00:00 +0000",
  "content": "Whether you’re skiing in the backcountry or trampolining in the backyard, we have an activity tracker for you.",
  "image": "https://media.wired.com/photos/61b26233c2f5f4d2aaf1c2b5/191:100/w_2580,c_limit/Gear-Fitbit-Charge-5.jpg",
  "description": "Whether you’re skiing in the backcountry or trampolining in the backyard, we have an activity tracker for you.",
  "publisher": "Wired",
  "publisherUrl": "https://www.wired.com/"
}