{
  "title": "The Enduring Legacy of Clubhouse’s Chatty Revolution",
  "url": "https://www.wired.com/story/enduring-legacy-clubhouses-chatty-revolution",
  "date": "Thu, 31 Mar 2022 12:00:00 +0000",
  "content": "The app’s buzz may have quieted down, but its spirit still animates the social internet.",
  "image": "https://media.wired.com/photos/62292f53e5e91991368ff659/191:100/w_1280,c_limit/WI040122_MG_Heffernan_Chartgeist_01.jpg",
  "description": "The app’s buzz may have quieted down, but its spirit still animates the social internet.",
  "publisher": "Wired",
  "publisherUrl": "https://www.wired.com/"
}