{
  "title": "The Best Turntables for Your Vinyl Collection",
  "url": "https://www.wired.com/gallery/best-turntables",
  "date": "Mon, 07 Feb 2022 14:00:00 +0000",
  "content": "Streaming music giving you the blues? These entry-level turntables will help you rock on to analog audio at home.",
  "image": "https://media.wired.com/photos/5efa52c344ebc430839b8254/191:100/w_2580,c_limit/Gear-Audio-Technica-ATLP120XUSB-SOURCE-Audio-Technica.jpg",
  "description": "Streaming music giving you the blues? These entry-level turntables will help you rock on to analog audio at home.",
  "publisher": "Wired",
  "publisherUrl": "https://www.wired.com/"
}