{
  "title": "Are you tired of your job or is it actually burnout?",
  "url": "https://www.futurity.org/work-burnout-2728172-2/?utm_source=rss&utm_medium=rss&utm_campaign=work-burnout-2728172-2",
  "date": "Wed, 20 Apr 2022 17:46:26 +0000",
  "content": "What are the signs of burnout at work and what can you do about it? An expert explains what to look for in yourself and others.",
  "image": "https://www.futurity.org/wp/wp-content/uploads/2022/04/work-burnout-signs-tips-1600.jpg",
  "description": "What are the signs of burnout at work and what can you do about it? An expert explains what to look for in yourself and others.",
  "publisher": "Futurity",
  "publisherUrl": "https://www.futurity.org/"
}