{
  "title": "Fastest GPS routes may have higher crash risk",
  "url": "https://www.futurity.org/gps-route-directions-road-safety-2704542/?utm_source=rss&utm_medium=rss&utm_campaign=gps-route-directions-road-safety-2704542",
  "date": "Tue, 01 Mar 2022 17:18:00 +0000",
  "content": "Your GPS may give you the fastest route to get to where you're going. But that doesn't mean it will be the safest one.",
  "image": "https://www.futurity.org/wp/wp-content/uploads/2022/03/gps-guidance-safety-1600.jpg",
  "description": "Your GPS may give you the fastest route to get to where you're going. But that doesn't mean it will be the safest one.",
  "publisher": "Futurity",
  "publisherUrl": "https://www.futurity.org/"
}